Workbook

Sheet 📊 Dashboard
B2: Budget 2026 | G2: 📊 Dashboard
B3: Your personal finance overview
B5: Total Income | D5: Total Expenses | F5: Net Savings | G5: Savings Rate
B6: ='📈 Annual Summary'!C15 -> 18185 | D6: ='📈 Annual Summary'!D15 -> 16405 | F6: ='📈 Annual Summary'!E15 -> 1780 | G6: =IF('📈 Annual Summary'!C15=0,"",'📈 Annual Summary'!E15/'📈 Annual Summary'!C15) -> 0.09788287
B9: Monthly Overview
B10: Month | C10: Income | D10: Expenses | E10: Net | F10: Rate | G10: Cumulative
B11: January | C11: ='📈 Annual Summary'!C3 -> 5945 | D11: ='📈 Annual Summary'!D3 -> 5305 | E11: =C11-D11 -> 640 | F11: =IF(C11=0,"",E11/C11) -> 0.10765349 | G11: =E11 -> 640
B12: February | C12: ='📈 Annual Summary'!C4 -> 6080 | D12: ='📈 Annual Summary'!D4 -> 5450 | E12: =C12-D12 -> 630 | F12: =IF(C12=0,"",E12/C12) -> 0.10361842 | G12: =G11+E12 -> 1270
B13: March | C13: ='📈 Annual Summary'!C5 -> 6160 | D13: ='📈 Annual Summary'!D5 -> 5650 | E13: =C13-D13 -> 510 | F13: =IF(C13=0,"",E13/C13) -> 0.082792208 | G13: =G12+E13 -> 1780
B14: April | C14: ='📈 Annual Summary'!C6 -> 0 | D14: ='📈 Annual Summary'!D6 -> 0 | E14: =C14-D14 -> 0 | F14: =IF(C14=0,"",E14/C14) | G14: =G13+E14 -> 1780
B15: May | C15: ='📈 Annual Summary'!C7 -> 0 | D15: ='📈 Annual Summary'!D7 -> 0 | E15: =C15-D15 -> 0 | F15: =IF(C15=0,"",E15/C15) | G15: =G14+E15 -> 1780
B16: June | C16: ='📈 Annual Summary'!C8 -> 0 | D16: ='📈 Annual Summary'!D8 -> 0 | E16: =C16-D16 -> 0 | F16: =IF(C16=0,"",E16/C16) | G16: =G15+E16 -> 1780
B17: July | C17: ='📈 Annual Summary'!C9 -> 0 | D17: ='📈 Annual Summary'!D9 -> 0 | E17: =C17-D17 -> 0 | F17: =IF(C17=0,"",E17/C17) | G17: =G16+E17 -> 1780
B18: August | C18: ='📈 Annual Summary'!C10 -> 0 | D18: ='📈 Annual Summary'!D10 -> 0 | E18: =C18-D18 -> 0 | F18: =IF(C18=0,"",E18/C18) | G18: =G17+E18 -> 1780
B19: September | C19: ='📈 Annual Summary'!C11 -> 0 | D19: ='📈 Annual Summary'!D11 -> 0 | E19: =C19-D19 -> 0 | F19: =IF(C19=0,"",E19/C19) | G19: =G18+E19 -> 1780
B20: October | C20: ='📈 Annual Summary'!C12 -> 0 | D20: ='📈 Annual Summary'!D12 -> 0 | E20: =C20-D20 -> 0 | F20: =IF(C20=0,"",E20/C20) | G20: =G19+E20 -> 1780
B21: November | C21: ='📈 Annual Summary'!C13 -> 0 | D21: ='📈 Annual Summary'!D13 -> 0 | E21: =C21-D21 -> 0 | F21: =IF(C21=0,"",E21/C21) | G21: =G20+E21 -> 1780
B22: December | C22: ='📈 Annual Summary'!C14 -> 0 | D22: ='📈 Annual Summary'!D14 -> 0 | E22: =C22-D22 -> 0 | F22: =IF(C22=0,"",E22/C22) | G22: =G21+E22 -> 1780
B23: Year Total | C23: =SUM(C11:C22) -> 18185 | D23: =SUM(D11:D22) -> 16405 | E23: =C23-D23 -> 1780 | F23: =IF(C23=0,"",E23/C23) -> 0.09788287 | G23: =G22 -> 1780
B25: ⚠️ This dashboard is read-only. Enter data in the 📋 Monthly Budget tab.

Sheet 📋 Monthly Budget
B1: JANUARY 2026
B3: INCOME
B4: Category | C4: Budgeted | D4: Actual | E4: Difference
B5: Salary/Wages | C5: 5000 | D5: 5000 | E5: =IF(AND(C5="",D5=""),"",D5-C5) -> 0
B6: Side Income | C6: 500 | D6: 450 | E6: =IF(AND(C6="",D6=""),"",D6-C6) -> -50
B7: Freelance/Business | C7: 300 | D7: 375 | E7: =IF(AND(C7="",D7=""),"",D7-C7) -> 75
B8: Investment Income | C8: 100 | D8: 120 | E8: =IF(AND(C8="",D8=""),"",D8-C8) -> 20
B9: Other Income | C9: 0 | D9: 0 | E9: =IF(AND(C9="",D9=""),"",D9-C9) -> 0
B10: TOTAL INCOME | C10: =SUM(C5:C9) -> 5900 | D10: =SUM(D5:D9) -> 5945 | E10: =D10-C10 -> 45
B12: EXPENSES
B13: Category | C13: Budgeted | D13: Actual | E13: Difference
B14: 🏠 HOUSING
B15: Rent/Mortgage | C15: 1500 | D15: 1500 | E15: =IF(AND(C15="",D15=""),"",C15-D15) -> 0
B16: Home Insurance | C16: 100 | D16: 100 | E16: =IF(AND(C16="",D16=""),"",C16-D16) -> 0
B17: Property Tax | C17: 200 | D17: 200 | E17: =IF(AND(C17="",D17=""),"",C17-D17) -> 0
B18: HOA Fees | C18: 50 | D18: 50 | E18: =IF(AND(C18="",D18=""),"",C18-D18) -> 0
B19: Maintenance/Repairs | C19: 50 | D19: 0 | E19: =IF(AND(C19="",D19=""),"",C19-D19) -> 50
B20: 🚗 TRANSPORTATION
B21: Car Payment | C21: 350 | D21: 350 | E21: =IF(AND(C21="",D21=""),"",C21-D21) -> 0
B22: Gas/Fuel | C22: 150 | D22: 165 | E22: =IF(AND(C22="",D22=""),"",C22-D22) -> -15
B23: Auto Insurance | C23: 100 | D23: 100 | E23: =IF(AND(C23="",D23=""),"",C23-D23) -> 0
B24: Car Maintenance | C24: 50 | D24: 0 | E24: =IF(AND(C24="",D24=""),"",C24-D24) -> 50
B25: Public Transit/Rideshare | C25: 30 | D25: 25 | E25: =IF(AND(C25="",D25=""),"",C25-D25) -> 5
B26: 🛒 GROCERIES & FOOD
B27: Groceries | C27: 500 | D27: 520 | E27: =IF(AND(C27="",D27=""),"",C27-D27) -> -20
B28: Dining Out | C28: 200 | D28: 245 | E28: =IF(AND(C28="",D28=""),"",C28-D28) -> -45
B29: Coffee/Snacks | C29: 50 | D29: 65 | E29: =IF(AND(C29="",D29=""),"",C29-D29) -> -15
B30: 💡 UTILITIES
B31: Electric | C31: 120 | D31: 115 | E31: =IF(AND(C31="",D31=""),"",C31-D31) -> 5
B32: Gas/Heating | C32: 80 | D32: 95 | E32: =IF(AND(C32="",D32=""),"",C32-D32) -> -15
B33: Water/Sewer | C33: 40 | D33: 40 | E33: =IF(AND(C33="",D33=""),"",C33-D33) -> 0
B34: Internet | C34: 60 | D34: 60 | E34: =IF(AND(C34="",D34=""),"",C34-D34) -> 0
B35: Phone | C35: 80 | D35: 80 | E35: =IF(AND(C35="",D35=""),"",C35-D35) -> 0
B36: 🏥 HEALTH
B37: Health Insurance | C37: 250 | D37: 250 | E37: =IF(AND(C37="",D37=""),"",C37-D37) -> 0
B38: Medications | C38: 30 | D38: 30 | E38: =IF(AND(C38="",D38=""),"",C38-D38) -> 0
B39: Doctor/Dental | C39: 50 | D39: 0 | E39: =IF(AND(C39="",D39=""),"",C39-D39) -> 50
B40: Gym/Fitness | C40: 40 | D40: 40 | E40: =IF(AND(C40="",D40=""),"",C40-D40) -> 0
B41: 🎓 EDUCATION
B42: Tuition/Student Loans | C42: 200 | D42: 200 | E42: =IF(AND(C42="",D42=""),"",C42-D42) -> 0
B43: Books/Supplies | C43: 20 | D43: 0 | E43: =IF(AND(C43="",D43=""),"",C43-D43) -> 20
B44: Online Courses | C44: 15 | D44: 15 | E44: =IF(AND(C44="",D44=""),"",C44-D44) -> 0
B45: 🛍️ PERSONAL
B46: Clothing | C46: 100 | D46: 75 | E46: =IF(AND(C46="",D46=""),"",C46-D46) -> 25
B47: Personal Care | C47: 40 | D47: 40 | E47: =IF(AND(C47="",D47=""),"",C47-D47) -> 0
B48: Subscriptions | C48: 50 | D48: 50 | E48: =IF(AND(C48="",D48=""),"",C48-D48) -> 0
B49: 🎉 ENTERTAINMENT
B50: Streaming Services | C50: 30 | D50: 30 | E50: =IF(AND(C50="",D50=""),"",C50-D50) -> 0
B51: Hobbies | C51: 50 | D51: 40 | E51: =IF(AND(C51="",D51=""),"",C51-D51) -> 10
B52: Events/Outings | C52: 75 | D52: 60 | E52: =IF(AND(C52="",D52=""),"",C52-D52) -> 15
B53: 💰 SAVINGS & DEBT
B54: Emergency Fund | C54: 200 | D54: 200 | E54: =IF(AND(C54="",D54=""),"",C54-D54) -> 0
B55: Investments/Retirement | C55: 300 | D55: 300 | E55: =IF(AND(C55="",D55=""),"",C55-D55) -> 0
B56: Debt Payments | C56: 150 | D56: 150 | E56: =IF(AND(C56="",D56=""),"",C56-D56) -> 0
B57: 📦 OTHER
B58: Gifts | C58: 50 | D58: 30 | E58: =IF(AND(C58="",D58=""),"",C58-D58) -> 20
B59: Donations/Charity | C59: 50 | D59: 50 | E59: =IF(AND(C59="",D59=""),"",C59-D59) -> 0
B60: Miscellaneous | C60: 50 | D60: 35 | E60: =IF(AND(C60="",D60=""),"",C60-D60) -> 15
B61: TOTAL EXPENSES | C61: =C15+C16+C17+C18+C19+C21+C22+C23+C24+C25+C27+C28+C29+C31+C32+C33+C34+C35+C37+C38+C39+C40+C42+C43+C44+C46+C47+C48+C50+C51+C52+C54+C55+C56+C58+C59+C60 -> 5460 | D61: =D15+D16+D17+D18+D19+D21+D22+D23+D24+D25+D27+D28+D29+D31+D32+D33+D34+D35+D37+D38+D39+D40+D42+D43+D44+D46+D47+D48+D50+D51+D52+D54+D55+D56+D58+D59+D60 -> 5305 | E61: =C61-D61 -> 155
B63: JANUARY SUMMARY
B64: Total Income | C64: =C10 -> 5900 | D64: =D10 -> 5945
B65: Total Expenses | C65: =C61 -> 5460 | D65: =D61 -> 5305
B66: Net (Income - Expenses) | C66: =C64-C65 -> 440 | D66: =D10-D61 -> 640
B67: Savings Rate | C67: =IF(C64=0,"",1-C65/C64) -> 0.074576271 | D67: =IF(D10=0,"",1-D61/D10) -> 0.10765349
B71: FEBRUARY 2026
B73: INCOME
B74: Category | C74: Budgeted | D74: Actual | E74: Difference
B75: Salary/Wages | D75: 5200 | E75: =IF(AND(C75="",D75=""),"",D75-C75) -> 5200
B76: Side Income | D76: 400 | E76: =IF(AND(C76="",D76=""),"",D76-C76) -> 400
B77: Freelance/Business | D77: 350 | E77: =IF(AND(C77="",D77=""),"",D77-C77) -> 350
B78: Investment Income | D78: 130 | E78: =IF(AND(C78="",D78=""),"",D78-C78) -> 130
B79: Other Income | D79: 0 | E79: =IF(AND(C79="",D79=""),"",D79-C79) -> 0
B80: TOTAL INCOME | C80: =SUM(C75:C79) -> 0 | D80: =SUM(D75:D79) -> 6080 | E80: =D80-C80 -> 6080
B82: EXPENSES
B83: Category | C83: Budgeted | D83: Actual | E83: Difference
B84: 🏠 HOUSING
B85: Rent/Mortgage | D85: 1500 | E85: =IF(AND(C85="",D85=""),"",C85-D85) -> -1500
B86: Home Insurance | D86: 100 | E86: =IF(AND(C86="",D86=""),"",C86-D86) -> -100
B87: Property Tax | D87: 200 | E87: =IF(AND(C87="",D87=""),"",C87-D87) -> -200
B88: HOA Fees | D88: 50 | E88: =IF(AND(C88="",D88=""),"",C88-D88) -> -50
B89: Maintenance/Repairs | D89: 75 | E89: =IF(AND(C89="",D89=""),"",C89-D89) -> -75
B90: 🚗 TRANSPORTATION
B91: Car Payment | D91: 350 | E91: =IF(AND(C91="",D91=""),"",C91-D91) -> -350
B92: Gas/Fuel | D92: 155 | E92: =IF(AND(C92="",D92=""),"",C92-D92) -> -155
B93: Auto Insurance | D93: 100 | E93: =IF(AND(C93="",D93=""),"",C93-D93) -> -100
B94: Car Maintenance | D94: 45 | E94: =IF(AND(C94="",D94=""),"",C94-D94) -> -45
B95: Public Transit/Rideshare | D95: 30 | E95: =IF(AND(C95="",D95=""),"",C95-D95) -> -30
B96: 🛒 GROCERIES & FOOD
B97: Groceries | D97: 480 | E97: =IF(AND(C97="",D97=""),"",C97-D97) -> -480
B98: Dining Out | D98: 210 | E98: =IF(AND(C98="",D98=""),"",C98-D98) -> -210
B99: Coffee/Snacks | D99: 55 | E99: =IF(AND(C99="",D99=""),"",C99-D99) -> -55
B100: 💡 UTILITIES
B101: Electric | D101: 125 | E101: =IF(AND(C101="",D101=""),"",C101-D101) -> -125
B102: Gas/Heating | D102: 85 | E102: =IF(AND(C102="",D102=""),"",C102-D102) -> -85
B103: Water/Sewer | D103: 40 | E103: =IF(AND(C103="",D103=""),"",C103-D103) -> -40
B104: Internet | D104: 60 | E104: =IF(AND(C104="",D104=""),"",C104-D104) -> -60
B105: Phone | D105: 80 | E105: =IF(AND(C105="",D105=""),"",C105-D105) -> -80
B106: 🏥 HEALTH
B107: Health Insurance | D107: 250 | E107: =IF(AND(C107="",D107=""),"",C107-D107) -> -250
B108: Medications | D108: 25 | E108: =IF(AND(C108="",D108=""),"",C108-D108) -> -25
...

Sheet 📈 Annual Summary
B1: ANNUAL SUMMARY 2026
B2: Month | C2: Total Income | D2: Total Expenses | E2: Net Savings | F2: Savings Rate | G2: Cumulative Savings
B3: January | C3: ='📋 Monthly Budget'!D10 -> 5945 | D3: ='📋 Monthly Budget'!D61 -> 5305 | E3: =C3-D3 -> 640 | F3: =IF(C3=0,"",E3/C3) -> 0.10765349 | G3: =E3 -> 640
B4: February | C4: ='📋 Monthly Budget'!D80 -> 6080 | D4: ='📋 Monthly Budget'!D131 -> 5450 | E4: =C4-D4 -> 630 | F4: =IF(C4=0,"",E4/C4) -> 0.10361842 | G4: =G3+E4 -> 1270
B5: March | C5: ='📋 Monthly Budget'!D150 -> 6160 | D5: ='📋 Monthly Budget'!D201 -> 5650 | E5: =C5-D5 -> 510 | F5: =IF(C5=0,"",E5/C5) -> 0.082792208 | G5: =G4+E5 -> 1780
B6: April | C6: ='📋 Monthly Budget'!D220 -> 0 | D6: ='📋 Monthly Budget'!D271 -> 0 | E6: =C6-D6 -> 0 | F6: =IF(C6=0,"",E6/C6) | G6: =G5+E6 -> 1780
B7: May | C7: ='📋 Monthly Budget'!D290 -> 0 | D7: ='📋 Monthly Budget'!D341 -> 0 | E7: =C7-D7 -> 0 | F7: =IF(C7=0,"",E7/C7) | G7: =G6+E7 -> 1780
B8: June | C8: ='📋 Monthly Budget'!D360 -> 0 | D8: ='📋 Monthly Budget'!D411 -> 0 | E8: =C8-D8 -> 0 | F8: =IF(C8=0,"",E8/C8) | G8: =G7+E8 -> 1780
B9: July | C9: ='📋 Monthly Budget'!D430 -> 0 | D9: ='📋 Monthly Budget'!D481 -> 0 | E9: =C9-D9 -> 0 | F9: =IF(C9=0,"",E9/C9) | G9: =G8+E9 -> 1780
B10: August | C10: ='📋 Monthly Budget'!D500 -> 0 | D10: ='📋 Monthly Budget'!D551 -> 0 | E10: =C10-D10 -> 0 | F10: =IF(C10=0,"",E10/C10) | G10: =G9+E10 -> 1780
B11: September | C11: ='📋 Monthly Budget'!D570 -> 0 | D11: ='📋 Monthly Budget'!D621 -> 0 | E11: =C11-D11 -> 0 | F11: =IF(C11=0,"",E11/C11) | G11: =G10+E11 -> 1780
B12: October | C12: ='📋 Monthly Budget'!D640 -> 0 | D12: ='📋 Monthly Budget'!D691 -> 0 | E12: =C12-D12 -> 0 | F12: =IF(C12=0,"",E12/C12) | G12: =G11+E12 -> 1780
B13: November | C13: ='📋 Monthly Budget'!D710 -> 0 | D13: ='📋 Monthly Budget'!D761 -> 0 | E13: =C13-D13 -> 0 | F13: =IF(C13=0,"",E13/C13) | G13: =G12+E13 -> 1780
B14: December | C14: ='📋 Monthly Budget'!D780 -> 0 | D14: ='📋 Monthly Budget'!D831 -> 0 | E14: =C14-D14 -> 0 | F14: =IF(C14=0,"",E14/C14) | G14: =G13+E14 -> 1780
B15: YEAR TOTAL | C15: =SUM(C3:C14) -> 18185 | D15: =SUM(D3:D14) -> 16405 | E15: =C15-D15 -> 1780 | F15: =IF(C15=0,"",E15/C15) -> 0.09788287 | G15: =G14 -> 1780
B16: MONTHLY AVERAGE | C16: =AVERAGE(C3:C14) -> 1515.4167 | D16: =AVERAGE(D3:D14) -> 1367.0833 | E16: =AVERAGE(E3:E14) -> 148.33333 | F16: =IF(C16=0,"",E16/C16) -> 0.09788287
B18: BEST & WORST MONTHS
B19: Best Savings Month | C19: =INDEX(B3:B14,MATCH(MAX(E3:E14),E3:E14,0)) -> January | E19: =MAX(E3:E14) -> 640
B20: Worst Savings Month | C20: =INDEX(B3:B14,MATCH(MIN(E3:E14),E3:E14,0)) -> April | E20: =MIN(E3:E14) -> 0
B21: Highest Spending Month | C21: =INDEX(B3:B14,MATCH(MAX(D3:D14),D3:D14,0)) -> March | E21: =MAX(D3:D14) -> 5650
B22: Highest Income Month | C22: =INDEX(B3:B14,MATCH(MAX(C3:C14),C3:C14,0)) -> March | E22: =MAX(C3:C14) -> 6160

Sheet ⚙️ Categories
B1: EXPENSE CATEGORIES & BUDGET SETTINGS
B2: Customize your expense categories below. Edit category names, set monthly budgets, and mark priority levels. These guide your monthly tracking on the Monthly Budget tab.
B4: PRIORITY LEGEND: | D4: Need = Essential | E4: Want = Optional | F4: Save = Savings/Investment
B6: # | C6: Category Name | D6: Monthly Budget | E6: Priority | F6: Notes
C7: 🏠 HOUSING | E7: Need
B8: 1 | C8: Rent/Mortgage | D8: 1500 | E8: Need
B9: 2 | C9: Home Insurance | D9: 100 | E9: Need
B10: 3 | C10: Property Tax | D10: 200 | E10: Need
B11: 4 | C11: HOA Fees | D11: 50 | E11: Need
B12: 5 | C12: Maintenance/Repairs | D12: 50 | E12: Need
C13: 🚗 TRANSPORTATION | E13: Need
B14: 6 | C14: Car Payment | D14: 350 | E14: Need
B15: 7 | C15: Gas/Fuel | D15: 150 | E15: Need
B16: 8 | C16: Auto Insurance | D16: 100 | E16: Need
B17: 9 | C17: Car Maintenance | D17: 50 | E17: Need
B18: 10 | C18: Public Transit/Rideshare | D18: 30 | E18: Need
C19: 🛒 GROCERIES & FOOD | E19: Need
B20: 11 | C20: Groceries | D20: 500 | E20: Need
B21: 12 | C21: Dining Out | D21: 200 | E21: Need
B22: 13 | C22: Coffee/Snacks | D22: 50 | E22: Need
C23: 💡 UTILITIES | E23: Need
B24: 14 | C24: Electric | D24: 120 | E24: Need
B25: 15 | C25: Gas/Heating | D25: 80 | E25: Need
B26: 16 | C26: Water/Sewer | D26: 40 | E26: Need
B27: 17 | C27: Internet | D27: 60 | E27: Need
B28: 18 | C28: Phone | D28: 80 | E28: Need
C29: 🏥 HEALTH | E29: Need
B30: 19 | C30: Health Insurance | D30: 250 | E30: Need
B31: 20 | C31: Medications | D31: 30 | E31: Need
B32: 21 | C32: Doctor/Dental | D32: 50 | E32: Need
B33: 22 | C33: Gym/Fitness | D33: 40 | E33: Need
C34: 🎓 EDUCATION | E34: Need
B35: 23 | C35: Tuition/Student Loans | D35: 200 | E35: Need
B36: 24 | C36: Books/Supplies | D36: 20 | E36: Need
B37: 25 | C37: Online Courses | D37: 15 | E37: Need
C38: 🛍️ PERSONAL | E38: Want
B39: 26 | C39: Clothing | D39: 100 | E39: Want
B40: 27 | C40: Personal Care | D40: 40 | E40: Want
B41: 28 | C41: Subscriptions | D41: 50 | E41: Want
C42: 🎉 ENTERTAINMENT | E42: Want
B43: 29 | C43: Streaming Services | D43: 30 | E43: Want
B44: 30 | C44: Hobbies | D44: 50 | E44: Want
B45: 31 | C45: Events/Outings | D45: 75 | E45: Want
C46: 💰 SAVINGS & DEBT | E46: Save
B47: 32 | C47: Emergency Fund | D47: 200 | E47: Save
B48: 33 | C48: Investments/Retirement | D48: 300 | E48: Save
B49: 34 | C49: Debt Payments | D49: 150 | E49: Save
C50: 📦 OTHER | E50: Want
B51: 35 | C51: Gifts | D51: 50 | E51: Want
B52: 36 | C52: Donations/Charity | D52: 50 | E52: Want
B53: 37 | C53: Miscellaneous | D53: 50 | E53: Want
C55: TOTAL MONTHLY BUDGET | D55: =SUM(D7:D54) -> 5460
C56: TOTAL ANNUAL BUDGET | D56: =D55*12 -> 65520

Sheet 📖 Instructions
B2: ANNUAL BUDGET PLANNER 2026
B3: Instructions & Getting Started Guide
B5: WELCOME
B6: Thank you for choosing the Annual Budget Planner 2026! This professionally designed spreadsheet will help you take control of your finances, track every dollar, and achieve your savings goals. Whether you are paying off debt, saving for a big purchase, or simply want to understand where your money goes, this planner has you covered.
B8: GETTING STARTED - STEP BY STEP
B9: Step 1: Make a Copy
B10: If using Google Sheets: File > Make a Copy. If using Excel: File > Save As. This ensures you always have a clean original template.
B11: Step 2: Set Your Categories
B12: Go to the Categories tab. Review the pre-filled expense categories and monthly budgets. Edit category names and budget amounts to match your personal spending patterns.
B13: Step 3: Plan Your January Budget
B14: Go to the Monthly Budget tab. For January, enter your expected income in the 'Budgeted' column. Then enter your planned spending for each expense category in the 'Budgeted' column.
B15: Step 4: Track Actual Spending
... B52: Version 1.0 | Annual Budget Planner 2026 | All Rights Reserved
